<keymap version="1" name="AMC" parent="Default for XWin">
  <action id="ActivateBigDataToolWindowToolWindow" />
  <action id="ActivateBookmarksToolWindow" />
  <action id="ActivateBuildToolWindow">
    <keyboard-shortcut first-keystroke="alt b" />
  </action>
  <action id="ActivateCheckStyleToolWindow">
    <keyboard-shortcut first-keystroke="alt y" />
  </action>
  <action id="ActivateCommitToolWindow">
    <keyboard-shortcut first-keystroke="alt c" />
  </action>
  <action id="ActivateCoverageToolWindow">
    <keyboard-shortcut first-keystroke="alt o" />
  </action>
  <action id="ActivateDatabaseToolWindow">
    <keyboard-shortcut first-keystroke="alt e" />
  </action>
  <action id="ActivateDebugToolWindow">
    <keyboard-shortcut first-keystroke="alt d" />
  </action>
  <action id="ActivateFindToolWindow">
    <keyboard-shortcut first-keystroke="alt f" />
  </action>
  <action id="ActivateNotificationsToolWindow">
    <keyboard-shortcut first-keystroke="alt n" />
  </action>
  <action id="ActivateProblemsViewToolWindow">
    <keyboard-shortcut first-keystroke="alt p" />
  </action>
  <action id="ActivateProjectToolWindow" />
  <action id="ActivateRunToolWindow">
    <keyboard-shortcut first-keystroke="alt r" />
  </action>
  <action id="ActivateServicesToolWindow" />
  <action id="ActivateStructureToolWindow">
    <keyboard-shortcut first-keystroke="alt t" />
  </action>
  <action id="ActivateVersionControlToolWindow">
    <keyboard-shortcut first-keystroke="alt g" />
  </action>
  <action id="ChangesView.ToggleCommitUi" />
  <action id="CheckinProject" />
  <action id="CompareTwoFiles" />
  <action id="CopyPaths" />
  <action id="CopyReference" />
  <action id="DatabaseView.CopyAction" />
  <action id="DatabaseView.CopyDdlAction" />
  <action id="Diff.ShowDiff" />
  <action id="EditorChooseLookupItemReplace" />
  <action id="EditorDown">
    <keyboard-shortcut first-keystroke="down" />
    <keyboard-shortcut first-keystroke="j" />
    <keyboard-shortcut first-keystroke="tab" />
  </action>
  <action id="EditorDuplicate" />
  <action id="EditorNextWordWithSelection" />
  <action id="EditorPageDown">
    <keyboard-shortcut first-keystroke="ctrl d" />
  </action>
  <action id="EditorPageUp">
    <keyboard-shortcut first-keystroke="ctrl u" />
  </action>
  <action id="EditorPreviousWordWithSelection" />
  <action id="EditorSelectWord" />
  <action id="EditorUp">
    <keyboard-shortcut first-keystroke="up" />
    <keyboard-shortcut first-keystroke="k" />
    <keyboard-shortcut first-keystroke="shift tab" />
  </action>
  <action id="ExportToTextFile" />
  <action id="FileChooser.GotoDesktop" />
  <action id="Git.Commit.Stage" />
  <action id="GotoAction">
    <keyboard-shortcut first-keystroke="alt a" />
  </action>
  <action id="GotoDeclaration" />
  <action id="GotoSuperMethod" />
  <action id="InsertInlineCompletionAction" />
  <action id="InsertLiveTemplate" />
  <action id="LivePlugin.RunPlugin" />
  <action id="LivePlugin.TestPlugin" />
  <action id="NextTab">
    <keyboard-shortcut first-keystroke="alt right" />
    <keyboard-shortcut first-keystroke="ctrl j" />
  </action>
  <action id="PasteMultiple" />
  <action id="PreviousTab">
    <keyboard-shortcut first-keystroke="alt left" />
    <keyboard-shortcut first-keystroke="ctrl k" />
  </action>
  <action id="Rerun" />
  <action id="RunDashboard.CopyConfiguration" />
  <action id="SendEOF" />
  <action id="ShowBookmarks" />
  <action id="SwitcherBackward">
    <keyboard-shortcut first-keystroke="ctrl l" />
  </action>
  <action id="SwitcherForward">
    <keyboard-shortcut first-keystroke="ctrl x" />
    <keyboard-shortcut first-keystroke="ctrl h" />
  </action>
  <action id="TypeHierarchy" />
  <action id="TypeHierarchyBase.BaseOnThisType" />
  <action id="UsageFiltering.WriteAccess" />
  <action id="Vcs.Log.FocusTextFilter" />
  <action id="Vcs.UpdateProject" />
  <action id="XDebugger.CopyWatch" />
  <action id="org.intellij.plugins.markdown.ui.actions.styling.InsertImageAction" />
  <action id="org.intellij.plugins.markdown.ui.actions.styling.ToggleCodeSpanAction" />
</keymap>